<?xml version="1.0" encoding="utf8"?>
<!DOCTYPE document PUBLIC "+//IDN docutils.sourceforge.net//DTD Docutils Generic//EN//XML" "http://docutils.sourceforge.net/docs/ref/docutils.dtd">
<!-- Generated by Docutils 0.13.1 -->
<document ids="interpreter-review" names="interpreter\ review" source="&lt;string&gt;" title="Interpreter Review"><title>Interpreter Review</title><subtitle ids="rp-24-part-1" names="rp\ 24\ part\ 1">RP 24 Part 1</subtitle><comment xml:space="preserve">This file is part of the OpenDSA eTextbook project. See</comment><comment xml:space="preserve">http://algoviz.org/OpenDSA for more details.</comment><comment xml:space="preserve">Copyright (c) 2012-13 by the OpenDSA Project Contributors, and</comment><comment xml:space="preserve">distributed under an MIT open source license.</comment><raw format="xml" xml:space="preserve"><avmetadata>null</avmetadata></raw><paragraph>This randomized problem will help you fully master the behavior of the
SLang 1 interpreter. Solve it correctly three times in a row to get
credit for it.</paragraph><raw format="xml" xml:space="preserve"><avembed
    type="ka"
    exer_name="RP24part1"
    long_name="RP24part1"
    points="1.0"
    required="True"
    threshold="5">
</avembed>
</raw></document>