{
  "chapters": {
    "Preface": {
      "Intro": {
        "long_name": "How to Use this System",
        "sections": null
      },
      "canvas_module_id": 1262281,
      "assignment_group_id": null
    },
    "Introduction": {
      "Background/IntroDSA": {
        "long_name": "Introduction to Data Structures and Algorithms",
        "sections": {
          "Data Structures and Algorithms": {
            "IntroSumm": {
              "long_name": "Introduction Summary Questions",
              "required": true,
              "points": 1.0,
              "threshold": 5.0
            },
            "module_item_id": 9896571,
            "item_id": 4863402
          },
          "Some Software Engineering Topics": null,
          "module_subheader_id": 9896569,
          "item_id": null
        }
      },
      "Design/ADT": {
        "long_name": "Abstract Data Types",
        "sections": {
          "Abstract Data Types": {
            "IntroADTSumm": {
              "long_name": "ADT Summary Questions",
              "required": true,
              "points": 1.0,
              "threshold": 4.0
            },
            "module_item_id": 9896575,
            "item_id": 4863403
          },
          "module_subheader_id": 9896573,
          "item_id": null
        }
      },
      "canvas_module_id": 1262282,
      "assignment_group_id": null
    },
    "Programming Tutorials": {
      "Tutorials/cmdline": {
        "long_name": "Command Line Basics",
        "sections": {
          "What's A CLI?": {
            "terminal": {
              "long_name": "Terminal",
              "required": false,
              "points": 0.0,
              "threshold": 1.0
            },
            "module_item_id": 9896577,
            "item_id": null
          },
          "module_subheader_id": 9896576,
          "item_id": null
        }
      },
      "Tutorials/parameters": {
        "long_name": "Parsing Command Line Parameters",
        "sections": {
          "Parameters In Programming": null,
          "module_subheader_id": 9896578,
          "item_id": null
        }
      },
      "Tutorials/eclipseparameters": {
        "long_name": "Using parameters in Eclipse",
        "sections": null
      },
      "Tutorials/webcattools": {
        "long_name": "Configuring Eclipse For Virginia Tech",
        "sections": null
      },
      "Tutorials/debugmethods": {
        "long_name": "Debugging Methods",
        "sections": null
      },
      "Tutorials/debug": {
        "long_name": "Debugging in Eclipse",
        "sections": null
      },
      "Tutorials/scanning": {
        "long_name": "Reading In Input",
        "sections": {
          "The Scanner Class": null,
          "module_subheader_id": 9896589,
          "item_id": null
        }
      },
      "Tutorials/randomaccessfile": {
        "long_name": "Using the Java RandomAccessFile class",
        "sections": {
          "Understanding File I/O": null,
          "module_subheader_id": 9896591,
          "item_id": null
        }
      },
      "Tutorials/junitstart": {
        "long_name": "Junit Testing and You",
        "sections": {
          "Getting Started": null,
          "module_subheader_id": 9896593,
          "item_id": null
        }
      },
      "Tutorials/junitbasic": {
        "long_name": "Writing JUnit Tests",
        "sections": null
      },
      "Tutorials/junitcoverage": {
        "long_name": "Junit tests and how to use them",
        "sections": null
      },
      "canvas_module_id": 1262283,
      "assignment_group_id": null
    },
    "Appendix": {
      "Glossary": {
        "long_name": "Glossary",
        "sections": null
      },
      "Bibliography": {
        "long_name": "Bibliography",
        "sections": null
      },
      "canvas_module_id": 1262284,
      "assignment_group_id": null
    }
  },
  "course_id": 1040936,
  "LMS_url": "https://canvas.instructure.com",
  "module_map": {
    "Bibliography": {
      "item_id": 41803
    },
    "AnalAsymptotic": {
      "assignment_id": 35989,
      "module_item_id": 41626
    },
    "InSort": {
      "item_id": 41704
    },
    "ListAnalysis": {
      "assignment_id": 36038,
      "module_item_id": 41759
    },
    "ListArray": {
      "item_id": 41744
    },
    "IntroOO": {
      "item_id": 41606
    },
    "RecIntro": {
      "item_id": 41647
    },
    "CodeCompletionEx": {
      "assignment_id": 35997,
      "module_item_id": 41652
    },
    "IntroProcess": {
      "item_id": 41610
    },
    "ListDouble": {
      "item_id": 41763
    },
    "AnalProgram": {
      "assignment_id": 35990,
      "module_item_id": 41629
    },
    "WritingEx": {
      "assignment_id": 36008,
      "module_item_id": 41678
    },
    "SelectionSort": {
      "assignment_id": 36025,
      "module_item_id": 41723
    },
    "BST": {
      "assignment_id": 36049,
      "module_item_id": 41793
    },
    "InsertionSort": {
      "assignment_id": 36021,
      "module_item_id": 41713
    },
    "BubbleSort": {
      "assignment_id": 36023,
      "module_item_id": 41718
    },
    "AlgAnalSumm": {
      "assignment_id": 35992,
      "module_item_id": 41634
    },
    "TracingEx": {
      "assignment_id": 36012,
      "module_item_id": 41689
    },
    "AnalCompvsAlg": {
      "assignment_id": 35988,
      "module_item_id": 41623
    },
    "Comparison": {
      "assignment_id": 36020,
      "module_item_id": 41710
    },
    "ADT": {
      "assignment_id": 35984,
      "module_item_id": 41604
    },
    "AnalIntro": {
      "assignment_id": 35986,
      "module_item_id": 41616
    },
    "Glossary": {
      "item_id": 41801
    },
    "BinaryTree": {
      "assignment_id": 36043,
      "module_item_id": 41778
    },
    "Queue": {
      "item_id": 41727
    },
    "BinaryTreeIntro": {
      "item_id": 41775
    },
    "ListSumm": {
      "assignment_id": 36041,
      "module_item_id": 41771
    },
    "StackLinked": {
      "assignment_id": 35995,
      "module_item_id": 41643
    },
    "Write": {
      "item_id": 41649
    },
    "Trace": {
      "item_id": 41686
    },
    "HarderCodeCompletionEx": {
      "assignment_id": 36005,
      "module_item_id": 41671
    },
    "HarderWrite": {
      "item_id": 41668
    },
    "IntroUML": {
      "item_id": 41608
    },
    "IntroDSA": {
      "assignment_id": 35983,
      "module_item_id": 41601
    },
    "AnalPrelim": {
      "assignment_id": 35985,
      "module_item_id": 41613
    },
    "QueueLinked": {
      "assignment_id": 36029,
      "module_item_id": 41735
    },
    "SortNotation": {
      "assignment_id": 36019,
      "module_item_id": 41707
    },
    "Intro": {
      "item_id": 41598
    },
    "Freelist": {
      "item_id": 41768
    },
    "ListLinked": {
      "item_id": 41752
    },
    "BinaryTreeTraversal": {
      "item_id": 41782
    },
    "RecSummaryEx": {
      "assignment_id": 36018,
      "module_item_id": 41702
    },
    "ListElement": {
      "assignment_id": 36040,
      "module_item_id": 41766
    },
    "AnalCases": {
      "item_id": 41620
    },
    "StackArray": {
      "item_id": 41636
    },
    "ListADT": {
      "assignment_id": 36032,
      "module_item_id": 41742
    }
  }
}